{"directed": true, "multigraph": false, "graph": {}, "nodes": [{"value": "20", "op": [], "id": 1}, {"value": "w", "op": [], "id": 2}, {"value": "-10", "op": ["-"], "id": 3}, {"value": "10", "op": [], "id": 4}, {"value": "p", "op": [], "id": 5}, {"value": "-30", "op": ["*"], "id": 6}, {"value": "2", "op": [], "id": 7}, {"value": "6idx0", "op": "*", "id": 8}, {"value": "4", "op": [], "id": 9}, {"value": "-20", "op": "-", "id": 10}, {"value": "8ridx0", "op": ["-"], "id": 11}, {"value": "5", "op": [], "id": 12}, {"value": "8final_ans", "op": "=", "id": 13}, {"value": "8idx0", "op": [], "id": 14}, {"value": "9idx0", "op": "*", "id": 15}, {"value": "10idx0", "op": "*", "id": 16}, {"value": "10idx1", "op": "-", "id": 17}, {"value": "16", "op": [], "id": 18}, {"value": "10ridx0", "op": ["+"], "id": 19}, {"value": "10final_ans", "op": "=", "id": 20}, {"value": "11ridx0", "op": ["-"], "id": 21}, {"value": "11final_ans", "op": "=", "id": 22}, {"value": "11idx0", "op": [], "id": 23}, {"value": "12idx0", "op": "-", "id": 24}, {"value": "12idx1", "op": "*", "id": 25}, {"value": "12ridx0", "op": ["+"], "id": 26}, {"value": "12final_ans", "op": "=", "id": 27}], "links": [{"source": 2, "target": 1}, {"source": 2, "target": 3}, {"source": 2, "target": 10}, {"source": 2, "target": 11}, {"source": 2, "target": 19}, {"source": 2, "target": 21}, {"source": 2, "target": 26}, {"source": 4, "target": 3}, {"source": 5, "target": 4}, {"source": 5, "target": 6}, {"source": 5, "target": 3}, {"source": 5, "target": 8}, {"source": 5, "target": 15}, {"source": 5, "target": 16}, {"source": 5, "target": 24}, {"source": 7, "target": 6}, {"source": 8, "target": 10}, {"source": 9, "target": 8}, {"source": 9, "target": 15}, {"source": 9, "target": 16}, {"source": 9, "target": 19}, {"source": 9, "target": 24}, {"source": 9, "target": 25}, {"source": 9, "target": 26}, {"source": 11, "target": 13}, {"source": 12, "target": 11}, {"source": 12, "target": 21}, {"source": 14, "target": 13}, {"source": 15, "target": 10}, {"source": 16, "target": 17}, {"source": 17, "target": 20}, {"source": 18, "target": 17}, {"source": 19, "target": 20}, {"source": 21, "target": 22}, {"source": 23, "target": 22}, {"source": 24, "target": 25}, {"source": 25, "target": 27}, {"source": 26, "target": 27}]}